{
    "items": [
        {
            "heroName": "Pu Tler Ling",
            "fallenDay": "2021-05-11",
            "heroAge": "60",
            "heroGender": "m",
            "fallenCity": "ဟားခါး",
            "fallenState": "ချင်း",
            "fallenPlace": "",
            "heroPlace": "ဟားခါးမြို့၊ ဈေးသစ်ရပ်ကွက်",
            "fallenCause": "May-9 တွင်စစ်တပ်မှဖမ်းဆီးသွား၊ နှိပ်စက်ခံရကာကျဆုံး"
        },
        {
            "heroName": "Pu Khamh Bawi",
            "fallenDay": "2021-05-11",
            "heroAge": "",
            "heroGender": "m",
            "fallenCity": "ဟားခါး",
            "fallenState": "ချင်း",
            "fallenPlace": "",
            "heroPlace": "ဟားခါးမြို့၊ ဈေးသစ်ရပ်ကွက်",
            "fallenCause": "May-9 တွင်စစ်တပ်မှဖမ်းဆီးသွား၊ နှိပ်စက်ခံရကာကျဆုံး"
        },
        {
            "heroName": "ဆလိုင်းဗန်ဘျက်လင်း (Salai Van Biak Ling)",
            "fallenDay": "2021-05-16",
            "heroAge": "",
            "heroGender": "m",
            "fallenCity": "ဟားခါး",
            "fallenState": "ချင်း",
            "fallenPlace": "",
            "heroPlace": "",
            "fallenCause": "ကျည်မှန်"
        },
        {
            "heroName": "ဆလိုင်းကျုံးပဲန်းလျန် (Cung Peng Lian)",
            "fallenDay": "2021-05-31",
            "heroAge": "",
            "heroGender": "m",
            "fallenCity": "ဟားခါး",
            "fallenState": "ချင်း",
            "fallenPlace": "ဟားခါး-မတူပီ ကားလမ်း၊ ဆူရ်ခွာကျေးရွာအနီး",
            "heroPlace": "",
            "fallenCause": "ကျည်မှန်"
        },
        {
            "heroName": "Salai Phun Sang",
            "fallenDay": "2021-06-05",
            "heroAge": "",
            "heroGender": "m",
            "fallenCity": "ဟားခါး",
            "fallenState": "ချင်း",
            "fallenPlace": "",
            "heroPlace": "",
            "fallenCause": "ဗုံးမှန်"
        },
        {
            "heroName": "Salai Tial Chawn",
            "fallenDay": "2021-06-05",
            "heroAge": "",
            "heroGender": "m",
            "fallenCity": "ဟားခါး",
            "fallenState": "ချင်း",
            "fallenPlace": "",
            "heroPlace": "",
            "fallenCause": "ဗုံးမှန်"
        },
        {
            "heroName": "Salai Lai Kulh Thang",
            "fallenDay": "2021-06-05",
            "heroAge": "",
            "heroGender": "m",
            "fallenCity": "ဟားခါး",
            "fallenState": "ချင်း",
            "fallenPlace": "",
            "heroPlace": "",
            "fallenCause": "ဗုံးမှန်"
        },
        {
            "heroName": "Pu Rual Cung",
            "fallenDay": "2021-11-08",
            "heroAge": "24",
            "heroGender": "m",
            "fallenCity": "ဟားခါး",
            "fallenState": "ချင်း",
            "fallenPlace": "",
            "heroPlace": "ဟားခါးမြို့နယ်၊ နှီယာန်လောန်ထာရ်ကျေးရွာ",
            "fallenCause": "Oct-12 တွင်ဖမ်းဆီးခံ၇၊ Nov-8 တွင် သေဆုံးကြောင်းသိရှိရ"
        },
        {
            "heroName": "ဦးရန်းဟူ Rang Hu",
            "fallenDay": "2022-03-05",
            "heroAge": "",
            "heroGender": "m",
            "fallenCity": "ဟားခါး",
            "fallenState": "ချင်း",
            "fallenPlace": "ဟားခါးမြို့နယ်၊ ခွန်ကျုံးရွာ",
            "heroPlace": "ဟားခါးမြို့နယ်၊ ခွန်ကျုံးရွာ",
            "fallenCause": "ကျည်မှန်"
        }
    ]
}