{
    "items": [
        {
            "heroName": "ကိုဇော်ငြိမ်းတင့်",
            "fallenDay": "2021-05-02",
            "heroAge": "20",
            "heroGender": "m",
            "fallenCity": "လောင်းလုံး",
            "fallenState": "တနင်္သာရီ",
            "fallenPlace": "",
            "heroPlace": "ထားဝယ်မြို့၊ လောင်းလုံးမြို့နယ်၊ မင်းရပ်",
            "fallenCause": "ကျည်မှန်"
        },
        {
            "heroName": "မအေးချို",
            "fallenDay": "2021-05-29",
            "heroAge": "29",
            "heroGender": "f",
            "fallenCity": "လောင်းလုံး",
            "fallenState": "တနင်္သာရီ",
            "fallenPlace": "လောင်းလုံးမြို့နယ် သဘော့ဆိပ်ကျေးရွာအုပ်စု (ချောင်း၀ပြင်ရွာ)",
            "heroPlace": "လောင်းလုံးမြို့နယ် သဘော့ဆိပ်ကျေးရွာအုပ်စု (ချောင်း၀ပြင်ရွာ)",
            "fallenCause": "ကျည်မှန်၊ အလောင်းအားစစ်တပ်မှသိမ်းသွား"
        },
        {
            "heroName": "ဒေါ်ဆန်းပို",
            "fallenDay": "2021-05-29",
            "heroAge": "46",
            "heroGender": "f",
            "fallenCity": "လောင်းလုံး",
            "fallenState": "တနင်္သာရီ",
            "fallenPlace": "လောင်းလုံးမြို့နယ် သဘော့ဆိပ်ကျေးရွာအုပ်စု (ချောင်း၀ပြင်ရွာ)",
            "heroPlace": "လောင်းလုံးမြို့နယ် သဘော့ဆိပ်ကျေးရွာအုပ်စု (ချောင်း၀ပြင်ရွာ)",
            "fallenCause": "ကျည်မှန်၊ အလောင်းအားစစ်တပ်မှသိမ်းသွား"
        },
        {
            "heroName": "ဦးသက်မိုး (ခ) ဂျပန်",
            "fallenDay": "2021-09-10",
            "heroAge": "",
            "heroGender": "m",
            "fallenCity": "လောင်းလုံး",
            "fallenState": "တနင်္သာရီ",
            "fallenPlace": "လောင်းလုံးမြို့နယ် ၀ဗျောရွာ",
            "heroPlace": "လောင်းလုံးမြို့နယ် ၀ဗျောရွာ",
            "fallenCause": "ကျည်မှန်"
        },
        {
            "heroName": "",
            "fallenDay": "2021-09-17",
            "heroAge": "15",
            "heroGender": "m",
            "fallenCity": "လောင်းလုံး",
            "fallenState": "တနင်္သာရီ",
            "fallenPlace": "လောင်းလုံးမြို့နယ်၊ ကဒက်ငယ်ထိန်ကျေးရွာ",
            "heroPlace": "လောင်းလုံးမြို့နယ်၊ ကဒက်ငယ်ထိန်ကျေးရွာ",
            "fallenCause": "ကျည်မှန်"
        },
        {
            "heroName": "ဦးနေနေ",
            "fallenDay": "2021-10-22",
            "heroAge": "",
            "heroGender": "m",
            "fallenCity": "လောင်းလုံး",
            "fallenState": "တနင်္သာရီ",
            "fallenPlace": "လောင်းလုံမြို့နယ်၊ ပန္ဒလဲကျေးရွာ",
            "heroPlace": "လောင်းလုံမြို့နယ်၊ ပန္ဒလဲကျေးရွာ",
            "fallenCause": "ကျည်မှန်"
        },
        {
            "heroName": "ဦးအုန်းနီ (ဦးအောင်မြင့်)",
            "fallenDay": "2021-10-22",
            "heroAge": "",
            "heroGender": "m",
            "fallenCity": "လောင်းလုံး",
            "fallenState": "တနင်္သာရီ",
            "fallenPlace": "လောင်းလုံမြို့နယ်၊ ပန္ဒလဲကျေးရွာ",
            "heroPlace": "လောင်းလုံမြို့နယ်၊ ပန္ဒလဲကျေးရွာ",
            "fallenCause": "ကျည်မှန်"
        },
        {
            "heroName": "",
            "fallenDay": "2021-11-11",
            "heroAge": "",
            "heroGender": "m",
            "fallenCity": "လောင်းလုံး",
            "fallenState": "တနင်္သာရီ",
            "fallenPlace": "လောင်းလုံးမြို့နယ်၊ မင်းရပ်ရွာနှင့် သာယာကုန်းရွာကြား",
            "heroPlace": "ထားဝယ်မြို့၊ ဇလွန်းရွာ",
            "fallenCause": "ကျည်မှန်"
        },
        {
            "heroName": "ကိုငြိမ်းချမ်း",
            "fallenDay": "2021-11-21",
            "heroAge": "",
            "heroGender": "m",
            "fallenCity": "လောင်းလုံး",
            "fallenState": "တနင်္သာရီ",
            "fallenPlace": "လောင်းလုံးမြို့နယ်တောင်ဘက်ရှိ ညင်းမော်ကျေးရွာအနီး",
            "heroPlace": "",
            "fallenCause": "ကျည်မှန်"
        },
        {
            "heroName": "",
            "fallenDay": "2021-12-09",
            "heroAge": "15",
            "heroGender": "f",
            "fallenCity": "လောင်းလုံး",
            "fallenState": "တနင်္သာရီ",
            "fallenPlace": "လောင်းလုံးမြို့နယ်၊ အောက်ရေဖြူကျေးရွာ",
            "heroPlace": "လောင်းလုံးမြို့နယ်၊ အောက်ရေဖြူကျေးရွာ",
            "fallenCause": "ဗုံးမှန်"
        },
        {
            "heroName": "",
            "fallenDay": "2021-12-24",
            "heroAge": "",
            "heroGender": "m",
            "fallenCity": "လောင်းလုံး",
            "fallenState": "တနင်္သာရီ",
            "fallenPlace": "",
            "heroPlace": "",
            "fallenCause": ""
        }
    ]
}