{
    "items": [
        {
            "heroName": "မောင်မောင်ဦး",
            "fallenDay": "2021-05-22",
            "heroAge": "19",
            "heroGender": "m",
            "fallenCity": "ဒီမောဆို",
            "fallenState": "ကယား",
            "fallenPlace": "ဒီးမော့ဆိုမြို့နယ်၊ ဒေါတဝီရွာ",
            "heroPlace": "ဒီးမော့ဆိုမြို့နယ်၊ ဒေါတဝီရွာ",
            "fallenCause": "ကျည်မှန်"
        },
        {
            "heroName": "ဘူးရီ",
            "fallenDay": "2021-05-22",
            "heroAge": "20",
            "heroGender": "m",
            "fallenCity": "ဒီမောဆို",
            "fallenState": "ကယား",
            "fallenPlace": "ဒီးမော့ဆိုမြို့နယ်၊ ဒေါတဝီရွာ",
            "heroPlace": "ဒီးမော့ဆိုမြို့နယ်၊ ဒေါတဝီရွာ",
            "fallenCause": "ကျည်မှန်"
        },
        {
            "heroName": "ကိုဖိုးဆွေ",
            "fallenDay": "2021-05-22",
            "heroAge": "35",
            "heroGender": "m",
            "fallenCity": "ကနီ",
            "fallenState": "စစ်ကိုင်း",
            "fallenPlace": "ကနီမြို့နယ်၊ သင်္ဂတုံချောင်းအနီး",
            "heroPlace": "ကနီမြို့နယ်၊ မြောင်းကုန်းရွာ",
            "fallenCause": "ကျည်မှန်၊ ဦးခေါင်းသို့ကျည်မှန်"
        },
        {
            "heroName": "ကိုစိုးလှိုင်ဖြိုး",
            "fallenDay": "2021-05-22",
            "heroAge": "23",
            "heroGender": "m",
            "fallenCity": "ကနီ",
            "fallenState": "စစ်ကိုင်း",
            "fallenPlace": "",
            "heroPlace": "ကနီမြို့နယ်၊ ခုံကြီးအုပ်စု ပါဟဲရွာ",
            "fallenCause": "ကျည်မှန်"
        },
        {
            "heroName": "",
            "fallenDay": "2021-05-22",
            "heroAge": "",
            "heroGender": "m",
            "fallenCity": "ကနီ",
            "fallenState": "စစ်ကိုင်း",
            "fallenPlace": "",
            "heroPlace": "ကနီမြို့နယ်၊ ကင်းအုပ်စု နံစုရွာ",
            "fallenCause": "ကျည်မှန်"
        },
        {
            "heroName": "",
            "fallenDay": "2021-05-22",
            "heroAge": "",
            "heroGender": "m",
            "fallenCity": "ကနီ",
            "fallenState": "စစ်ကိုင်း",
            "fallenPlace": "ကနီ-မင်းကင်းလမ်း",
            "heroPlace": "",
            "fallenCause": "ကျည်မှန်"
        },
        {
            "heroName": "",
            "fallenDay": "2021-05-22",
            "heroAge": "",
            "heroGender": "m",
            "fallenCity": "ကနီ",
            "fallenState": "စစ်ကိုင်း",
            "fallenPlace": "ကနီ-မင်းကင်းလမ်း",
            "heroPlace": "",
            "fallenCause": "ကျည်မှန်"
        },
        {
            "heroName": "",
            "fallenDay": "2021-05-22",
            "heroAge": "",
            "heroGender": "m",
            "fallenCity": "ကနီ",
            "fallenState": "စစ်ကိုင်း",
            "fallenPlace": "",
            "heroPlace": "",
            "fallenCause": "ကျည်မှန်"
        }
    ]
}