{
    "items": [
        {
            "heroName": "ကိုတိုးဇော်အောင်",
            "fallenDay": "2021-03-25",
            "heroAge": "19",
            "heroGender": "m",
            "fallenCity": "ခင်ဦး",
            "fallenState": "စစ်ကိုင်း",
            "fallenPlace": "",
            "heroPlace": "ခင်ဦးမြို့၊ ကံသစ်ရွာ",
            "fallenCause": "ကျည်မှန်၊ ကုသနေသည့် ယာယီဆေးခန်းမှ ဖမ်းဆီးသွား"
        },
        {
            "heroName": "ကိုဇော်ဝင်းမောင်",
            "fallenDay": "2021-03-25",
            "heroAge": "19",
            "heroGender": "m",
            "fallenCity": "ခင်ဦး",
            "fallenState": "စစ်ကိုင်း",
            "fallenPlace": "",
            "heroPlace": "ခင်ဦးမြို့၊ မြကန်သာရပ်ကွက်",
            "fallenCause": "ကျည်မှန်၊ ကုသနေသည့် ယာယီဆေးခန်းမှ ဖမ်းဆီးသွား"
        },
        {
            "heroName": "",
            "fallenDay": "2021-06-19",
            "heroAge": "",
            "heroGender": "m",
            "fallenCity": "ခင်ဦး",
            "fallenState": "စစ်ကိုင်း",
            "fallenPlace": "ခင်ဦးမြို့နယ်၊ သာဂရနှင့်မြင်းဒေါင်းကြား၊ မူးတိမ်ချောင်းတံတားအနီး",
            "heroPlace": "",
            "fallenCause": "ကျည်မှန်"
        },
        {
            "heroName": "",
            "fallenDay": "2021-06-19",
            "heroAge": "",
            "heroGender": "m",
            "fallenCity": "ခင်ဦး",
            "fallenState": "စစ်ကိုင်း",
            "fallenPlace": "ခင်ဦးမြို့နယ်၊ သာဂရနှင့်မြင်းဒေါင်းကြား၊ မူးတိမ်ချောင်းတံတားအနီး",
            "heroPlace": "",
            "fallenCause": "ကျည်မှန်"
        },
        {
            "heroName": "ဦးမောင်အေး",
            "fallenDay": "2021-08-21",
            "heroAge": "35",
            "heroGender": "m",
            "fallenCity": "ခင်ဦး",
            "fallenState": "စစ်ကိုင်း",
            "fallenPlace": "ခင်ဦးမြို့၊ ကန်သာယာကျေးရွာ၊ တံတားလိန်အနီး",
            "heroPlace": "ခင်ဦးမြို့နယ်၊ ကံသစ်ကျေးရွာ",
            "fallenCause": "ကျည်မှန်၊ ဦးခေါင်းသို့ကျည်မှန်"
        },
        {
            "heroName": "ဒေါ်နွဲ့နွဲ့",
            "fallenDay": "2021-08-21",
            "heroAge": "35",
            "heroGender": "f",
            "fallenCity": "ခင်ဦး",
            "fallenState": "စစ်ကိုင်း",
            "fallenPlace": "ခင်ဦးမြို့၊ ကန်သာယာကျေးရွာ၊ တံတားလိန်အနီး",
            "heroPlace": "ခင်ဦးမြို့နယ်၊ ကံသစ်ကျေးရွာ",
            "fallenCause": "ကျည်မှန်၊ ဦးခေါင်းသို့ကျည်မှန်"
        },
        {
            "heroName": "ကိုထွန်းမြင့်နိုင်",
            "fallenDay": "2021-09-11",
            "heroAge": "26",
            "heroGender": "m",
            "fallenCity": "ခင်ဦး",
            "fallenState": "စစ်ကိုင်း",
            "fallenPlace": "ခင်ဦးမြို့နယ်၊ ကံသစ်ကျေးရွာ",
            "heroPlace": "ခင်ဦးမြို့နယ်၊ ကံသစ်ကျေးရွာ",
            "fallenCause": "ကျည်မှန်"
        },
        {
            "heroName": "",
            "fallenDay": "2021-09-11",
            "heroAge": "",
            "heroGender": "",
            "fallenCity": "ခင်ဦး",
            "fallenState": "စစ်ကိုင်း",
            "fallenPlace": "",
            "heroPlace": "",
            "fallenCause": "ကျည်မှန်၊ အလောင်းအား စစ်တပ်မှသိမ်းသွား"
        },
        {
            "heroName": "",
            "fallenDay": "2021-09-11",
            "heroAge": "",
            "heroGender": "",
            "fallenCity": "ခင်ဦး",
            "fallenState": "စစ်ကိုင်း",
            "fallenPlace": "",
            "heroPlace": "",
            "fallenCause": "ကျည်မှန်၊ အလောင်းအား စစ်တပ်မှသိမ်းသွား"
        },
        {
            "heroName": "ကိုစိုးမိုးအောင်",
            "fallenDay": "2021-09-26",
            "heroAge": "30",
            "heroGender": "m",
            "fallenCity": "ခင်ဦး",
            "fallenState": "စစ်ကိုင်း",
            "fallenPlace": "ခင်ဦးမြို့နယ်၊ မှန်တောနဲ့ အောင်သာရွာကြားရှိ ကွမ်းခြံ",
            "heroPlace": "ခင်ဦးမြို့နယ်၊ မှန်တောကျေးရွာ",
            "fallenCause": "ကျည်မှန်"
        },
        {
            "heroName": "ကိုမျိုးမြင့်အောင်",
            "fallenDay": "2021-09-26",
            "heroAge": "30",
            "heroGender": "m",
            "fallenCity": "ခင်ဦး",
            "fallenState": "စစ်ကိုင်း",
            "fallenPlace": "ခင်ဦးမြို့နယ်၊ မှန်တောနဲ့ အောင်သာရွာကြားရှိ ကွမ်းခြံ",
            "heroPlace": "ခင်ဦးမြို့နယ်၊ မှန်တောကျေးရွာ",
            "fallenCause": "ကျည်မှန်"
        },
        {
            "heroName": "ဒေါက်တာအောင်မြတ်မင်း",
            "fallenDay": "2021-09-26",
            "heroAge": "30",
            "heroGender": "m",
            "fallenCity": "ခင်ဦး",
            "fallenState": "စစ်ကိုင်း",
            "fallenPlace": "ခင်ဦးမြို့နယ်၊ မှန်တောနဲ့ အောင်သာရွာကြားရှိ ကွမ်းခြံ",
            "heroPlace": "ခင်ဦးမြို့နယ်၊ မှန်တောကျေးရွာ",
            "fallenCause": "ကျည်မှန်"
        },
        {
            "heroName": "မမျိုးသန္တာလှိုင်",
            "fallenDay": "2021-10-01",
            "heroAge": "",
            "heroGender": "f",
            "fallenCity": "ခင်ဦး",
            "fallenState": "စစ်ကိုင်း",
            "fallenPlace": "ခင်ဦးမြို့နယ်၊ ပျဉ်ထောင်ကျေးရွာ",
            "heroPlace": "ခင်ဦးမြို့နယ်၊ ပျဉ်ထောင်ကျေးရွာ",
            "fallenCause": "ကျည်မှန်"
        },
        {
            "heroName": "ကိုထွန်းစီ",
            "fallenDay": "2021-10-01",
            "heroAge": "",
            "heroGender": "m",
            "fallenCity": "ခင်ဦး",
            "fallenState": "စစ်ကိုင်း",
            "fallenPlace": "ခင်ဦးမြို့နယ်၊ ပျဉ်ထောင်ကျေးရွာ",
            "heroPlace": "ခင်ဦးမြို့နယ်၊ ပျဉ်ထောင်ကျေးရွာ",
            "fallenCause": "ကျည်မှန်"
        },
        {
            "heroName": "ကိုအောင်ဦး",
            "fallenDay": "2021-10-01",
            "heroAge": "",
            "heroGender": "m",
            "fallenCity": "ခင်ဦး",
            "fallenState": "စစ်ကိုင်း",
            "fallenPlace": "ခင်ဦးမြို့နယ်၊ ပျဉ်ထောင်ကျေးရွာ",
            "heroPlace": "ခင်ဦးမြို့နယ်၊ ပျဉ်ထောင်ကျေးရွာ",
            "fallenCause": "ကျည်မှန်"
        },
        {
            "heroName": "ကိုပုချို",
            "fallenDay": "2021-10-01",
            "heroAge": "",
            "heroGender": "m",
            "fallenCity": "ခင်ဦး",
            "fallenState": "စစ်ကိုင်း",
            "fallenPlace": "ခင်ဦးမြို့နယ်၊ ပျဉ်ထောင်ကျေးရွာ",
            "heroPlace": "ခင်ဦးမြို့နယ်၊ ပျဉ်ထောင်ကျေးရွာ",
            "fallenCause": "ကျည်မှန်"
        },
        {
            "heroName": "ဒေါ်ပု",
            "fallenDay": "2021-10-01",
            "heroAge": "",
            "heroGender": "m",
            "fallenCity": "ခင်ဦး",
            "fallenState": "စစ်ကိုင်း",
            "fallenPlace": "ခင်ဦးမြို့နယ်၊ ပျဉ်ထောင်ကျေးရွာ",
            "heroPlace": "ခင်ဦးမြို့နယ်၊ ပျဉ်ထောင်ကျေးရွာ",
            "fallenCause": "ကျည်မှန်"
        },
        {
            "heroName": "ဦးရွှေဘို (ခ) ဦးဝေမိုးနိုင်",
            "fallenDay": "2021-10-02",
            "heroAge": "",
            "heroGender": "m",
            "fallenCity": "ခင်ဦး",
            "fallenState": "စစ်ကိုင်း",
            "fallenPlace": "ခင်ဦးမြို့နယ်၊ ပျဉ်ထောင်ကျေးရွာ",
            "heroPlace": "",
            "fallenCause": "ကျည်မှန်"
        },
        {
            "heroName": "ကိုအောင်ဖြိုး",
            "fallenDay": "2021-10-03",
            "heroAge": "37",
            "heroGender": "m",
            "fallenCity": "ခင်ဦး",
            "fallenState": "စစ်ကိုင်း",
            "fallenPlace": "ခင်ဦးမြို့နယ်၊ ပျဉ်ထောင်ကျေးရွာ",
            "heroPlace": "ခင်ဦးမြို့နယ်၊ ရွှေကူတဲစုကျေးရွာ",
            "fallenCause": "ကျည်မှန်၊ ဦးခေါင်းသို့ကျည်မှန်"
        },
        {
            "heroName": "ကိုအောင်မြင့်စိုး (ခ) ဘာဂျာ",
            "fallenDay": "2021-10-03",
            "heroAge": "40",
            "heroGender": "m",
            "fallenCity": "ခင်ဦး",
            "fallenState": "စစ်ကိုင်း",
            "fallenPlace": "ခင်ဦးမြို့နယ်၊ ပျဉ်ထောင်ကျေးရွာ",
            "heroPlace": "ခင်ဦးမြို့နယ်၊ ရွှေကူတဲစုကျေးရွာ",
            "fallenCause": "ကျည်မှန်၊ ဦးခေါင်းသို့ကျည်မှန်"
        },
        {
            "heroName": "ဦးစိန်ပို",
            "fallenDay": "2021-10-03",
            "heroAge": "50",
            "heroGender": "m",
            "fallenCity": "ခင်ဦး",
            "fallenState": "စစ်ကိုင်း",
            "fallenPlace": "ခင်ဦးမြို့နယ်၊ ပျဉ်ထောင်ကျေးရွာ",
            "heroPlace": "ခင်ဦးမြို့နယ်၊ ရွှေကူတဲစုကျေးရွာ",
            "fallenCause": "ကျည်မှန်၊ ဦးခေါင်းသို့ကျည်မှန်"
        },
        {
            "heroName": "ကိုမျိုးဆွေ",
            "fallenDay": "2021-10-16",
            "heroAge": "",
            "heroGender": "m",
            "fallenCity": "ခင်ဦး",
            "fallenState": "စစ်ကိုင်း",
            "fallenPlace": "ခင်ဦးမြို့နယ်၊ ပျည်ထောင်ကျေးရွာထိပ်",
            "heroPlace": "ခင်ဦးမြို့နယ်၊ သဲစုကျေးရွာ",
            "fallenCause": "ရိုက်နှက်ခံရကာသေဆုံး"
        },
        {
            "heroName": "ကိုဇော်မင်းထွန်း",
            "fallenDay": "2021-10-24",
            "heroAge": "40",
            "heroGender": "m",
            "fallenCity": "ခင်ဦး",
            "fallenState": "စစ်ကိုင်း",
            "fallenPlace": "ခင်ဦးမြို့နယ်၊ ရွာသစ်ကုန်းကျေးရွာအနီးရှိ အောင်မြေဘုန်းကြီးကျောင်းအနောက်ဘက်",
            "heroPlace": "ခင်ဦးမြို့နယ်၊ ရွာသစ်ကုန်းကျေးရွာ",
            "fallenCause": "ကျည်မှန်၊ မီးရှို့သတ်ဖြတ်ခံရ"
        },
        {
            "heroName": "ကိုအောင်နိုင်ဦး",
            "fallenDay": "2021-10-30",
            "heroAge": "21",
            "heroGender": "m",
            "fallenCity": "ခင်ဦး",
            "fallenState": "စစ်ကိုင်း",
            "fallenPlace": "ခင်ဦးမြို့နယ်၊ ရွာသစ်ကုန်းကျေးရွာတောင်ဘက် ယာတောကြား",
            "heroPlace": "ခင်ဦးမြို့နယ်၊ ယောက်သွားအိုင်ကျေးရွာ",
            "fallenCause": "ကျည်မှန်"
        },
        {
            "heroName": "ကိုဖြိုးဝေအောင်",
            "fallenDay": "2021-11-01",
            "heroAge": "23",
            "heroGender": "m",
            "fallenCity": "ခင်ဦး",
            "fallenState": "စစ်ကိုင်း",
            "fallenPlace": "ခင်ဦးမြို့နယ်၊ သရက်ကန်ကျေးရွာ",
            "heroPlace": "ခင်ဦးမြို့နယ်၊ သရက်ကန်ကျေးရွာ",
            "fallenCause": "ကျည်မှန်"
        },
        {
            "heroName": "ကိုရန်နိုင်",
            "fallenDay": "2021-11-01",
            "heroAge": "30",
            "heroGender": "m",
            "fallenCity": "ခင်ဦး",
            "fallenState": "စစ်ကိုင်း",
            "fallenPlace": "ခင်ဦးမြို့နယ်၊ သရက်ကန်ကျေးရွာ",
            "heroPlace": "ခင်ဦးမြို့နယ်၊ မြနန္ဒာရပ်ကွက်",
            "fallenCause": "ကျည်မှန်"
        },
        {
            "heroName": "ကိုချစ်ကို",
            "fallenDay": "2021-11-01",
            "heroAge": "28",
            "heroGender": "m",
            "fallenCity": "ခင်ဦး",
            "fallenState": "စစ်ကိုင်း",
            "fallenPlace": "ခင်ဦးမြို့နယ်၊ သရက်ကန်ကျေးရွာ",
            "heroPlace": "ခင်ဦးမြို့နယ်၊ သရက်ကန်ကျေးရွာ",
            "fallenCause": "ကျည်မှန်"
        },
        {
            "heroName": "ဦးသာအေး",
            "fallenDay": "2021-11-13",
            "heroAge": "60",
            "heroGender": "m",
            "fallenCity": "ခင်ဦး",
            "fallenState": "စစ်ကိုင်း",
            "fallenPlace": "",
            "heroPlace": "ခင်ဦးမြို့နယ်၊ မရမ်းအင်းကျေးရွာ",
            "fallenCause": "ကျည်မှန်"
        },
        {
            "heroName": "ကိုမောင်မောင်ထွေး",
            "fallenDay": "2021-11-18",
            "heroAge": "",
            "heroGender": "m",
            "fallenCity": "ခင်ဦး",
            "fallenState": "စစ်ကိုင်း",
            "fallenPlace": "ခင်ဦးမြို့နယ် သဲကုန်းကြီးကျေးရွာ",
            "heroPlace": "ခင်ဦးမြို့နယ် သဲကုန်းကြီးကျေးရွာ",
            "fallenCause": "သတ်ဖြတ်ခံရ"
        },
        {
            "heroName": "မောင်ချစ်ကောင်း",
            "fallenDay": "2022-01-06",
            "heroAge": "12",
            "heroGender": "m",
            "fallenCity": "ခင်ဦး",
            "fallenState": "စစ်ကိုင်း",
            "fallenPlace": "ခင်ဦးမြို့နယ်၊ ကံသစ်ရွာ",
            "heroPlace": "ရွှေဘိုမြို့နယ်၊ ရွာတော်ရွာ",
            "fallenCause": "ကျည်မှန်"
        },
        {
            "heroName": "ဦးကိုဦး",
            "fallenDay": "2022-01-19",
            "heroAge": "",
            "heroGender": "m",
            "fallenCity": "ခင်ဦး",
            "fallenState": "စစ်ကိုင်း",
            "fallenPlace": "ခင်ဦးမြို့နယ်၊ လက်ပံလှရွာ",
            "heroPlace": "ခင်ဦးမြို့နယ်၊ လက်ပံလှရွာ",
            "fallenCause": "ကျည်မှန်"
        },
        {
            "heroName": "မောင်ပိုင်ဇေရဲထွန်း",
            "fallenDay": "2022-02-08",
            "heroAge": "15",
            "heroGender": "m",
            "fallenCity": "ခင်ဦး",
            "fallenState": "စစ်ကိုင်း",
            "fallenPlace": "ခင်ဦးမြို့နယ်၊ မဒေါင်းကြီးကျေးရွာ",
            "heroPlace": "ခင်ဦးမြို့နယ်၊ မဒေါင်းကြီးကျေးရွာ",
            "fallenCause": "သတ်ဖြတ်ခံရ"
        },
        {
            "heroName": "ဦးလှထွန်း",
            "fallenDay": "2022-02-08",
            "heroAge": "",
            "heroGender": "m",
            "fallenCity": "ခင်ဦး",
            "fallenState": "စစ်ကိုင်း",
            "fallenPlace": "ခင်ဦးမြို့နယ်၊ မဒေါင်းကြီးကျေးရွာ",
            "heroPlace": "ခင်ဦးမြို့နယ်၊ မဒေါင်းကြီးကျေးရွာ",
            "fallenCause": "သတ်ဖြတ်ခံရ"
        },
        {
            "heroName": "",
            "fallenDay": "2022-02-10",
            "heroAge": "",
            "heroGender": "m",
            "fallenCity": "ခင်ဦး",
            "fallenState": "စစ်ကိုင်း",
            "fallenPlace": "",
            "heroPlace": "ခင်းဦးမြို့နယ်၊ ကုလားလူးကျေးရွာ",
            "fallenCause": "ကျည်မှန်"
        },
        {
            "heroName": "ကိုဇော်လှိုင်မိုး",
            "fallenDay": "2022-02-17",
            "heroAge": "22",
            "heroGender": "m",
            "fallenCity": "ခင်ဦး",
            "fallenState": "စစ်ကိုင်း",
            "fallenPlace": "ခင်ဦးမြို့နယ်၊ မြို့သစ်ရွာနှင့် ကံကြီးကုန်းရွာတိုက်ပွဲ",
            "heroPlace": "",
            "fallenCause": "လက်နက်ကြီးမှန်"
        },
        {
            "heroName": "မောင်မင်းသက်အောင်",
            "fallenDay": "2022-02-17",
            "heroAge": "15",
            "heroGender": "m",
            "fallenCity": "ခင်ဦး",
            "fallenState": "စစ်ကိုင်း",
            "fallenPlace": "ခင်ဦးမြို့နယ်၊ မြို့သစ်ရွာနှင့် ကံကြီးကုန်းရွာတိုက်ပွဲ",
            "heroPlace": "",
            "fallenCause": "လက်နက်ကြီးမှန်"
        },
        {
            "heroName": "ကိုရွှေဘုန်း",
            "fallenDay": "2022-02-17",
            "heroAge": "18",
            "heroGender": "m",
            "fallenCity": "ခင်ဦး",
            "fallenState": "စစ်ကိုင်း",
            "fallenPlace": "ခင်ဦးမြို့နယ်၊ မြို့သစ်ရွာနှင့် ကံကြီးကုန်းရွာတိုက်ပွဲ",
            "heroPlace": "",
            "fallenCause": "လက်နက်ကြီးမှန်"
        },
        {
            "heroName": "ကိုဖိုးသားကြီး",
            "fallenDay": "2022-02-17",
            "heroAge": "27",
            "heroGender": "m",
            "fallenCity": "ခင်ဦး",
            "fallenState": "စစ်ကိုင်း",
            "fallenPlace": "ခင်ဦးမြို့နယ်၊ မြို့သစ်ရွာနှင့် ကံကြီးကုန်းရွာတိုက်ပွဲ",
            "heroPlace": "",
            "fallenCause": "လက်နက်ကြီးမှန်"
        },
        {
            "heroName": "ကိုလင်းထက်အောင်",
            "fallenDay": "2022-02-17",
            "heroAge": "18",
            "heroGender": "m",
            "fallenCity": "ခင်ဦး",
            "fallenState": "စစ်ကိုင်း",
            "fallenPlace": "ခင်ဦးမြို့နယ်၊ မြို့သစ်ရွာနှင့် ကံကြီးကုန်းရွာတိုက်ပွဲ",
            "heroPlace": "",
            "fallenCause": "လက်နက်ကြီးမှန်"
        },
        {
            "heroName": "ကိုဇော်မင်းထွန်း",
            "fallenDay": "2022-02-17",
            "heroAge": "26",
            "heroGender": "m",
            "fallenCity": "ခင်ဦး",
            "fallenState": "စစ်ကိုင်း",
            "fallenPlace": "ခင်ဦးမြို့နယ်၊ မြို့သစ်ရွာနှင့် ကံကြီးကုန်းရွာတိုက်ပွဲ",
            "heroPlace": "",
            "fallenCause": "လက်နက်ကြီးမှန်"
        },
        {
            "heroName": "ကိုထွန်းထွန်းဝင်း",
            "fallenDay": "2022-02-17",
            "heroAge": "40",
            "heroGender": "m",
            "fallenCity": "ခင်ဦး",
            "fallenState": "စစ်ကိုင်း",
            "fallenPlace": "ခင်ဦးမြို့နယ်၊ မြို့သစ်ရွာနှင့် ကံကြီးကုန်းရွာတိုက်ပွဲ",
            "heroPlace": "",
            "fallenCause": "လက်နက်ကြီးမှန်"
        },
        {
            "heroName": "ကိုကျော်မိုး",
            "fallenDay": "2022-02-17",
            "heroAge": "39",
            "heroGender": "m",
            "fallenCity": "ခင်ဦး",
            "fallenState": "စစ်ကိုင်း",
            "fallenPlace": "ခင်ဦးမြို့နယ်၊ မြို့သစ်ရွာနှင့် ကံကြီးကုန်းရွာတိုက်ပွဲ",
            "heroPlace": "",
            "fallenCause": "လက်နက်ကြီးမှန်"
        },
        {
            "heroName": "မောင်အောင်ထက်",
            "fallenDay": "2022-02-17",
            "heroAge": "15",
            "heroGender": "m",
            "fallenCity": "ခင်ဦး",
            "fallenState": "စစ်ကိုင်း",
            "fallenPlace": "ခင်ဦးမြို့နယ်၊ မြို့သစ်ရွာနှင့် ကံကြီးကုန်းရွာတိုက်ပွဲ",
            "heroPlace": "",
            "fallenCause": "လက်နက်ကြီးမှန်"
        },
        {
            "heroName": "ကိုစိုင်းမင်းထွေး",
            "fallenDay": "2022-02-17",
            "heroAge": "19",
            "heroGender": "m",
            "fallenCity": "ခင်ဦး",
            "fallenState": "စစ်ကိုင်း",
            "fallenPlace": "ခင်ဦးမြို့နယ်၊ မြို့သစ်ရွာနှင့် ကံကြီးကုန်းရွာတိုက်ပွဲ",
            "heroPlace": "",
            "fallenCause": "လက်နက်ကြီးမှန်"
        },
        {
            "heroName": "ကိုဇော်မိုက်",
            "fallenDay": "2022-02-17",
            "heroAge": "22",
            "heroGender": "m",
            "fallenCity": "ခင်ဦး",
            "fallenState": "စစ်ကိုင်း",
            "fallenPlace": "ခင်ဦးမြို့နယ်၊ မြို့သစ်ရွာနှင့် ကံကြီးကုန်းရွာတိုက်ပွဲ",
            "heroPlace": "",
            "fallenCause": "လက်နက်ကြီးမှန်"
        },
        {
            "heroName": "ကိုလှိုင်း",
            "fallenDay": "2022-02-17",
            "heroAge": "22",
            "heroGender": "m",
            "fallenCity": "ခင်ဦး",
            "fallenState": "စစ်ကိုင်း",
            "fallenPlace": "ခင်ဦးမြို့နယ်၊ မြို့သစ်ရွာနှင့် ကံကြီးကုန်းရွာတိုက်ပွဲ",
            "heroPlace": "",
            "fallenCause": "လက်နက်ကြီးမှန်"
        },
        {
            "heroName": "ကိုကျောက်ထက်",
            "fallenDay": "2022-02-17",
            "heroAge": "19",
            "heroGender": "m",
            "fallenCity": "ခင်ဦး",
            "fallenState": "စစ်ကိုင်း",
            "fallenPlace": "ခင်ဦးမြို့နယ်၊ မြို့သစ်ရွာနှင့် ကံကြီးကုန်းရွာတိုက်ပွဲ",
            "heroPlace": "",
            "fallenCause": "လက်နက်ကြီးမှန်"
        },
        {
            "heroName": "ဦးစောထွေး",
            "fallenDay": "2022-02-17",
            "heroAge": "49",
            "heroGender": "m",
            "fallenCity": "ခင်ဦး",
            "fallenState": "စစ်ကိုင်း",
            "fallenPlace": "ခင်ဦးမြို့နယ်၊ မြို့သစ်ရွာနှင့် ကံကြီးကုန်းရွာတိုက်ပွဲ",
            "heroPlace": "",
            "fallenCause": "လက်နက်ကြီးမှန်"
        }
    ]
}