{
    "items": [
        {
            "heroName": "",
            "fallenDay": "2021-09-29",
            "heroAge": "",
            "heroGender": "",
            "fallenCity": "ထီးချိုင့်",
            "fallenState": "စစ်ကိုင်း",
            "fallenPlace": "ထီးချိုင့်မြို့နယ်၊ တည်တောကျေးရွာအနီး",
            "heroPlace": "",
            "fallenCause": "ကျည်မှန်"
        },
        {
            "heroName": "",
            "fallenDay": "2021-09-29",
            "heroAge": "",
            "heroGender": "",
            "fallenCity": "ထီးချိုင့်",
            "fallenState": "စစ်ကိုင်း",
            "fallenPlace": "ထီးချိုင့်မြို့နယ်၊ တည်တောကျေးရွာအနီး",
            "heroPlace": "",
            "fallenCause": "ကျည်မှန်"
        },
        {
            "heroName": "",
            "fallenDay": "2021-10-08",
            "heroAge": "",
            "heroGender": "m",
            "fallenCity": "ထီးချိုင့်",
            "fallenState": "စစ်ကိုင်း",
            "fallenPlace": "",
            "heroPlace": "ထီးချိုင့်မြို့နယ်၊ အင်းတိန်ရွာ",
            "fallenCause": "စစ်ကြောရေးတွင်သေဆုံး"
        }
    ]
}