{
    "items": [
        {
            "heroName": "ဒေါ်ကြီးမိန်",
            "fallenDay": "2021-06-15",
            "heroAge": "",
            "heroGender": "f",
            "fallenCity": "ပေါက်",
            "fallenState": "မကွေး",
            "fallenPlace": "ပေါက်မြို့နယ်၊ ကင်းမကျေးရွာ",
            "heroPlace": "ပေါက်မြို့နယ်၊ ကင်းမကျေးရွာ",
            "fallenCause": "မီးရှို့သတ်ခံရ"
        },
        {
            "heroName": "ဦးမြမောင်",
            "fallenDay": "2021-06-15",
            "heroAge": "",
            "heroGender": "m",
            "fallenCity": "ပေါက်",
            "fallenState": "မကွေး",
            "fallenPlace": "ပေါက်မြို့နယ်၊ ကင်းမကျေးရွာ",
            "heroPlace": "ပေါက်မြို့နယ်၊ ကင်းမကျေးရွာ",
            "fallenCause": "မီးရှို့သတ်ခံရ"
        },
        {
            "heroName": "",
            "fallenDay": "2021-07-29",
            "heroAge": "",
            "heroGender": "m",
            "fallenCity": "ပေါက်",
            "fallenState": "မကွေး",
            "fallenPlace": "ပေါက်မြို့နယ်၊ ကြည့်ငိုတောင်သွားရာလမ်းအနီး",
            "heroPlace": "",
            "fallenCause": "မြေမြှုပ်မိုင်းနင်းမိ"
        },
        {
            "heroName": "",
            "fallenDay": "2021-07-29",
            "heroAge": "",
            "heroGender": "m",
            "fallenCity": "ပေါက်",
            "fallenState": "မကွေး",
            "fallenPlace": "ပေါက်မြို့နယ်၊ ကြည့်ငိုတောင်သွားရာလမ်းအနီး",
            "heroPlace": "",
            "fallenCause": "မြေမြှုပ်မိုင်းနင်းမိ"
        },
        {
            "heroName": "ကိုညိုသန်း",
            "fallenDay": "2021-08-27",
            "heroAge": "33",
            "heroGender": "m",
            "fallenCity": "ပေါက်",
            "fallenState": "မကွေး",
            "fallenPlace": "ပေါက်မြို့နယ်၊ ဒိန်းကွင်းကျေးရွာ",
            "heroPlace": "ပေါက်မြို့နယ်၊ ဒိန်းကွင်းကျေးရွာ",
            "fallenCause": "မီးရှို့သတ်ဖြတ်ခံရ"
        },
        {
            "heroName": "ဦးစိုးနိုင်ဝင်း",
            "fallenDay": "2021-08-27",
            "heroAge": "46",
            "heroGender": "m",
            "fallenCity": "ပေါက်",
            "fallenState": "မကွေး",
            "fallenPlace": "ပေါက်မြို့နယ်၊ ဒိန်းကွင်းကျေးရွာ",
            "heroPlace": "ပေါက်မြို့နယ်၊ ဒိန်းကွင်းကျေးရွာ",
            "fallenCause": "မီးရှို့သတ်ဖြတ်ခံရ"
        },
        {
            "heroName": "ကိုမင်းမင်း",
            "fallenDay": "2021-08-27",
            "heroAge": "38",
            "heroGender": "m",
            "fallenCity": "ပေါက်",
            "fallenState": "မကွေး",
            "fallenPlace": "ပေါက်မြို့နယ်၊ ဒိန်းကွင်းကျေးရွာ",
            "heroPlace": "ပေါက်မြို့နယ်၊ ဒိန်းကွင်းကျေးရွာ",
            "fallenCause": "မီးရှို့သတ်ဖြတ်ခံရ"
        },
        {
            "heroName": "",
            "fallenDay": "2021-08-28",
            "heroAge": "",
            "heroGender": "m",
            "fallenCity": "ပေါက်",
            "fallenState": "မကွေး",
            "fallenPlace": "ပေါက်မြို့နယ်၊ ကင်းမကျေးရွာ",
            "heroPlace": "ပေါက်မြို့နယ်၊ ကင်းမကျေးရွာ",
            "fallenCause": "မီးရှို့သတ်ဖြတ်ခံရ"
        },
        {
            "heroName": "",
            "fallenDay": "2021-08-28",
            "heroAge": "",
            "heroGender": "m",
            "fallenCity": "ပေါက်",
            "fallenState": "မကွေး",
            "fallenPlace": "ပေါက်မြို့နယ်၊ ကင်းမကျေးရွာ",
            "heroPlace": "ပေါက်မြို့နယ်၊ ကင်းမကျေးရွာ",
            "fallenCause": "မီးရှို့သတ်ဖြတ်ခံရ"
        },
        {
            "heroName": "ဦးညွန့်ရွှေ",
            "fallenDay": "2021-08-28",
            "heroAge": "",
            "heroGender": "m",
            "fallenCity": "ပေါက်",
            "fallenState": "မကွေး",
            "fallenPlace": "ပေါက်မြို့နယ်၊ ကင်းမကျေးရွာ",
            "heroPlace": "ပေါက်မြို့နယ်၊ ကင်းမကျေးရွာ",
            "fallenCause": "မီးရှို့သတ်ဖြတ်ခံရ"
        },
        {
            "heroName": "",
            "fallenDay": "2021-08-31",
            "heroAge": "",
            "heroGender": "m",
            "fallenCity": "ပေါက်",
            "fallenState": "မကွေး",
            "fallenPlace": "",
            "heroPlace": "",
            "fallenCause": ""
        },
        {
            "heroName": "မစန္ဒာဝင်း",
            "fallenDay": "2021-09-14",
            "heroAge": "42",
            "heroGender": "f",
            "fallenCity": "ပေါက်",
            "fallenState": "မကွေး",
            "fallenPlace": "ပေါက်မြို့နယ်၊ တောင်ဘက်ရွာ",
            "heroPlace": "ပေါက်မြို့နယ်၊ တောင်ဘက်ရွာ",
            "fallenCause": "ကျည်မှန်၊ ဦးခေါင်းသို့ကျည်မှန်"
        },
        {
            "heroName": "ဦးဘစိန်",
            "fallenDay": "2021-09-29",
            "heroAge": "",
            "heroGender": "m",
            "fallenCity": "ပေါက်",
            "fallenState": "မကွေး",
            "fallenPlace": "ပေါက်မြို့နယ်၊ အိုင်ကျယ်ကျေးရွာ",
            "heroPlace": "ပေါက်မြို့နယ်၊ ဝန်းခြုံကျေးရွာ",
            "fallenCause": "စစ်ဘေးရှောင်နေရာသို့ စစ်တပ်ဝင်စီးစဉ် နှလုံးရပ်ကာသေဆုံး"
        },
        {
            "heroName": "",
            "fallenDay": "2021-12-19",
            "heroAge": "",
            "heroGender": "m",
            "fallenCity": "ပေါက်",
            "fallenState": "မကွေး",
            "fallenPlace": "ပေါက်မြို့နယ်၊ ကျွန်းရင်းကျေးရွာအနီး",
            "heroPlace": "",
            "fallenCause": "ထောင်ဖမ်းခံရပြီး သတ်ဖြတ်ခံရ"
        },
        {
            "heroName": "ဦးမြင့်ရွှေ",
            "fallenDay": "2021-12-31",
            "heroAge": "",
            "heroGender": "m",
            "fallenCity": "ပေါက်",
            "fallenState": "မကွေး",
            "fallenPlace": "ပေါက်မြို့နယ်၊ ဇီးတောကျေးရွာနှင့် တောင်ဘက်ကျေးရွာကြား",
            "heroPlace": "ပေါက်မြို့နယ်၊ ဇီးတောကျေးရွာ",
            "fallenCause": "ကျည်မှန်"
        }
    ]
}