{
    "items": [
        {
            "heroName": "မောင်နောင်နောင်(ခ) မိုဟမ္မဒ်အလီ",
            "fallenDay": "2021-03-27",
            "heroAge": "16",
            "heroGender": "m",
            "fallenCity": "အမရပူရ",
            "fallenState": "မန္တလေး",
            "fallenPlace": "",
            "heroPlace": "အမရပူရမြို့နယ် ဘုံးအိုးကျေးရွာ",
            "fallenCause": "ကျည်မှန်"
        },
        {
            "heroName": "ကိုချစ်ဖူးသူ",
            "fallenDay": "2021-03-27",
            "heroAge": "19",
            "heroGender": "m",
            "fallenCity": "အမရပူရ",
            "fallenState": "မန္တလေး",
            "fallenPlace": "",
            "heroPlace": "သာလေစွ ရပ်ကွက်၊ ငယ်တိုးတိုက်နယ်",
            "fallenCause": "ကျည်မှန်"
        },
        {
            "heroName": "ကိုချစ်သက်ဦး",
            "fallenDay": "2021-03-27",
            "heroAge": "",
            "heroGender": "m",
            "fallenCity": "အမရပူရ",
            "fallenState": "မန္တလေး",
            "fallenPlace": "",
            "heroPlace": "အမရပူရမြို့နယ် တောင်ကြီးရပ်ကွက်",
            "fallenCause": "ကျည်မှန်"
        },
        {
            "heroName": "",
            "fallenDay": "2022-03-02",
            "heroAge": "",
            "heroGender": "m",
            "fallenCity": "အမရပူရ",
            "fallenState": "မန္တလေး",
            "fallenPlace": "အမရပူရမြို့နယ်၊ မှန်တန်းရပ်ကွက်၊ နန်းတော်ရာစံပြကွက်သစ်၊ နယ်မြေ(၅)",
            "heroPlace": "",
            "fallenCause": "ကျည်မှန်"
        }
    ]
}