{
    "items": [
        {
            "heroName": "ကိုဖိုးချစ်",
            "fallenDay": "2021-03-03",
            "heroAge": "22",
            "heroGender": "m",
            "fallenCity": "မြောက်ဥက္ကလာပ",
            "fallenState": "ရန်ကုန်",
            "fallenPlace": "မြောက်ဥက္ကလာ အဝိုင်းအနီး",
            "heroPlace": "၄၈ရပ်ကွက် ရှင်တရာလမ်း နာ/ကူ မရောက်ခင် မြောက်ဒဂုံ တံတားအဆင်း ညာဘက်ခြမ်း",
            "fallenCause": "ကျည်မှန်၊ ဆီမီးအော်တိုမက်တစ်ရိုင်ဖယ်ဖြင့် ပစ်ခံရ"
        },
        {
            "heroName": "ကိုထွန်းလင်းအောင်",
            "fallenDay": "2021-03-13",
            "heroAge": "22",
            "heroGender": "m",
            "fallenCity": "တွံတေး",
            "fallenState": "ရန်ကုန်",
            "fallenPlace": "",
            "heroPlace": "",
            "fallenCause": "ကျည်မှန်၊ ဦးခေါင်းသို့ကျည်မှန်"
        },
        {
            "heroName": "ကိုဝေဖြိုး",
            "fallenDay": "2021-03-14",
            "heroAge": "22",
            "heroGender": "m",
            "fallenCity": "လှိုင်သာယာ",
            "fallenState": "ရန်ကုန်",
            "fallenPlace": "",
            "heroPlace": "",
            "fallenCause": "ကျည်မှန်"
        },
        {
            "heroName": "မောင်ဟန်ထက်အောင်",
            "fallenDay": "2021-03-14",
            "heroAge": "22",
            "heroGender": "m",
            "fallenCity": "မြောက်ဥက္ကလာပ",
            "fallenState": "ရန်ကုန်",
            "fallenPlace": "",
            "heroPlace": "",
            "fallenCause": "ကျည်မှန်"
        },
        {
            "heroName": "ကိုဟိန်းစိုး (ခ) ဖိုးသဲ",
            "fallenDay": "2021-03-14",
            "heroAge": "22",
            "heroGender": "m",
            "fallenCity": "တောင်ဒဂုံ",
            "fallenState": "ရန်ကုန်",
            "fallenPlace": "တောင်ဒဂုံမြို့နယ်၊ ဧရာဝဏ်လမ်း၊ သစ်ဆိုင်ကွေ့မှတ်တိုင်အနီး",
            "heroPlace": "",
            "fallenCause": "ကျည်မှန်"
        },
        {
            "heroName": "ကိုဝေဖြိုးသိန်း",
            "fallenDay": "2021-03-15",
            "heroAge": "22",
            "heroGender": "m",
            "fallenCity": "မန္တလေး",
            "fallenState": "မန္တလေး",
            "fallenPlace": "မန္တလေးမြို့ ချမ်းမြသာစည်မြို့နယ် မြရည်နန္ဒာရပ်ကွက် ၁၁၂ A လမ်း၊ ၅၄  လမ်းနှင့် ၅၅ လမ်းကြား",
            "heroPlace": "မန္တလေးမြို့၊ မြရည်နန္ဒာအိမ်ယာရပ်ကွက်၊ ၁၁၂လမ်းA၊  ၅၄/၅၅ လမ်းကြား",
            "fallenCause": "ကျည်မှန်၊ ရင်ဘတ်သို့ ကျည်မှန်"
        },
        {
            "heroName": "ကိုနန္ဒဖြိုးအောင်",
            "fallenDay": "2021-03-15",
            "heroAge": "22",
            "heroGender": "m",
            "fallenCity": "ဒဂုံမြို့သစ် (ဆိပ်ကမ်း)",
            "fallenState": "ရန်ကုန်",
            "fallenPlace": "ဒဂုံဆိပ်ကမ်းမြို့နယ်၊ ယုဇနဥယျာဥ်မြို့တော်၊ ပုဏ္ဏမီလမ်းမကြီး (အိုးအိမ်)အနီး",
            "heroPlace": "ဒဂုံဆိပ်ကမ်းမြို့နယ်၊ ၉၄ ရပ်ကွက်၊ A block ၉လမ်း၊ တိုက်(၁)၊အခန်း(၃၀၃)",
            "fallenCause": "ကျည်မှန်၊ ကျည်မှန်ဒဏ်ရာ အသက်ရှင်လျှက်ဖြင့် စစ်တပ်မှသိမ်သွား၊"
        },
        {
            "heroName": "ကိုကျော်မင်းထွန်း",
            "fallenDay": "2021-03-16",
            "heroAge": "22",
            "heroGender": "m",
            "fallenCity": "ကောလင်း",
            "fallenState": "စစ်ကိုင်း",
            "fallenPlace": "",
            "heroPlace": "ကောလင်းမြို့နယ်၊ မင်းကုန်းကျေးရွာ",
            "fallenCause": "ကျည်မှန်"
        },
        {
            "heroName": "မအေးအေးခိုင်  (ခ) ရိုစာနာဘီ",
            "fallenDay": "2021-03-18",
            "heroAge": "22",
            "heroGender": "f",
            "fallenCity": "မြောက်ဥက္ကလာပ",
            "fallenState": "ရန်ကုန်",
            "fallenPlace": "မြောက်ဥက္ကလာပမြိုနယ် ၁/ ရပ်ကွက်၊ ဘုန်းကြီးလမ်းအနီး",
            "heroPlace": "",
            "fallenCause": "ကျည်မှန်၊ ဗိုက်သို့ကျည်မှန်"
        },
        {
            "heroName": "ကိုမင်းထက်နိုင် (ခ) ရှမ်းလေး",
            "fallenDay": "2021-03-19",
            "heroAge": "22",
            "heroGender": "m",
            "fallenCity": "အောင်ပန်း",
            "fallenState": "ရှမ်း",
            "fallenPlace": "",
            "heroPlace": "",
            "fallenCause": "ကျည်မှန်၊ အလောင်းအား စစ်တပ်မှသိမ်းသွားကာ စစ်တပ်မှ သဂြိုဟ်"
        },
        {
            "heroName": "ကိုချစ်ဘိုဘိုငြိမ်း (ခ) အာရားရား",
            "fallenDay": "2021-03-27",
            "heroAge": "22",
            "heroGender": "m",
            "fallenCity": "အင်းစိန်",
            "fallenState": "ရန်ကုန်",
            "fallenPlace": "အင်းစိန်မြို့နယ် ရွာမအနောက်လမ်း",
            "heroPlace": "အင်းစိန်မြို့နယ်၊ ရွာမအနောက်ရပ်ကွက်",
            "fallenCause": "ကျည်မှန်၊ ဘယ်ဘက် ချိုင်းအောက်သို့ ကျည်မှန်"
        },
        {
            "heroName": "မိုင်းမင်းနောင်",
            "fallenDay": "2021-03-27",
            "heroAge": "22",
            "heroGender": "m",
            "fallenCity": "လားရှိုး",
            "fallenState": "ရှမ်း",
            "fallenPlace": "",
            "heroPlace": "",
            "fallenCause": "ကျည်မှန်"
        },
        {
            "heroName": "ကိုရဲဇင်ဝင်း",
            "fallenDay": "2021-03-27",
            "heroAge": "22",
            "heroGender": "m",
            "fallenCity": "ပြင်ဦးလွင်",
            "fallenState": "မန္တလေး",
            "fallenPlace": "",
            "heroPlace": "ပြင်ဦးလွင်၊ စည်ကားရွာ",
            "fallenCause": "ကျည်မှန်၊ ဦးခေါင်းသို့ကျည်မှန်"
        },
        {
            "heroName": "ကိုဝေလု",
            "fallenDay": "2021-03-27",
            "heroAge": "22",
            "heroGender": "m",
            "fallenCity": "မရမ်းကုန်း",
            "fallenState": "ရန်ကုန်",
            "fallenPlace": "မရမ်းကုန်းမြို့နယ်၊ သမိုင်းဘူတာအနီး၊ မာလာလမ်း",
            "heroPlace": "",
            "fallenCause": "ကျည်မှန်၊ ဦးခေါင်းသို့ ကျည်မှန်"
        },
        {
            "heroName": "ကိုသန့်ဇင်ဦး",
            "fallenDay": "2021-03-30",
            "heroAge": "22",
            "heroGender": "m",
            "fallenCity": "ကော့သောင်း",
            "fallenState": "တနင်္သာရီ",
            "fallenPlace": "",
            "heroPlace": "",
            "fallenCause": "ကျည်မှန်"
        },
        {
            "heroName": "ကိုအာကာသူအောင် (ခ) Lian te",
            "fallenDay": "2021-04-07",
            "heroAge": "22",
            "heroGender": "m",
            "fallenCity": "ကလေး",
            "fallenState": "စစ်ကိုင်း",
            "fallenPlace": "ကလေးမြို့၊ တာဟန်းရပ်",
            "heroPlace": "",
            "fallenCause": "ကျည်မှန်"
        },
        {
            "heroName": "ကိုချမ်းမြေ့",
            "fallenDay": "2021-04-07",
            "heroAge": "22",
            "heroGender": "m",
            "fallenCity": "ပဲခူး",
            "fallenState": "ပဲခူး",
            "fallenPlace": "ပဲခူးမြို့၊ ကျောက်ကြီးစုရပ်",
            "heroPlace": "ပဲခူးမြို့ ကျောက်ကြီးစုရပ်ကွက် တိုးချဲ့လမ်းမ",
            "fallenCause": "ကျည်မှန်၊ ဦးခေါင်းသို့ကျည်မှန်"
        },
        {
            "heroName": "ကိုအိုက်လင်း",
            "fallenDay": "2021-04-12",
            "heroAge": "22",
            "heroGender": "f",
            "fallenCity": "မိုးမောက်",
            "fallenState": "ကချင်",
            "fallenPlace": "မိုးမောက်မြို့နယ်၊ ရွှေမြောင်းကျေးရွာ",
            "heroPlace": "မိုးမောက်မြို့နယ်၊ ရွှေမြောင်းကျေးရွာ",
            "fallenCause": "လက်နက်ကြီးမှန်"
        },
        {
            "heroName": "ကိုဂျူလီယံ",
            "fallenDay": "2021-04-24",
            "heroAge": "22",
            "heroGender": "m",
            "fallenCity": "လွိုင်ကော်",
            "fallenState": "ကယား",
            "fallenPlace": "လွိုင်ကော်မြို့၊ ဘီလူးချောင်း",
            "heroPlace": "",
            "fallenCause": "ဆန္ဒပြပွဲတွင် ရဲများဖမ်းဆီးသဖြင့် ချောင်းထဲခုန်ချကာ \bကျဆုံး"
        },
        {
            "heroName": "ကိုကောင်းထက်နိုင်",
            "fallenDay": "2021-04-24",
            "heroAge": "22",
            "heroGender": "m",
            "fallenCity": "မန္တလေး",
            "fallenState": "မန္တလေး",
            "fallenPlace": "ချမ်းမြသာစည်မြို့နယ်၊ ၆၅ လမ်း/ ၁၀၇ လမ်းအနီး",
            "heroPlace": "",
            "fallenCause": "ကျည်မှန်၊ ဗိုက်သို့ကျည်မှန်၊ အလောင်းအားစစ်တပ်မှသိမ်းသွား"
        },
        {
            "heroName": "ထန်မွန်းလျန် (Thang Muan Lian)",
            "fallenDay": "2021-04-27",
            "heroAge": "22",
            "heroGender": "m",
            "fallenCity": "တီးတီန်",
            "fallenState": "ချင်း",
            "fallenPlace": "",
            "heroPlace": "",
            "fallenCause": "ကျည်မှန်"
        },
        {
            "heroName": "ကိုမင်းဇင်",
            "fallenDay": "2021-05-02",
            "heroAge": "22",
            "heroGender": "m",
            "fallenCity": "ဝက်လက်",
            "fallenState": "စစ်ကိုင်း",
            "fallenPlace": "",
            "heroPlace": "",
            "fallenCause": "ကျည်မှန်၊ အလောင်းအားစစ်တပ်မှသိမ်းသွား"
        },
        {
            "heroName": "လဂျူဂျာဂွန်းတန်",
            "fallenDay": "2021-05-10",
            "heroAge": "22",
            "heroGender": "m",
            "fallenCity": "မိုးကောင်း",
            "fallenState": "ကချင်",
            "fallenPlace": "မိုးကောင်းမြို့နယ်၊ နမ္မတီးမြို့၊ မြို့မချယ်ရီခေါက်ဆွဲဆိုင်အနီး",
            "heroPlace": "မြစ်ကြီးနားမြို့၊ ကြာရာပါတီရပ်ကွက်",
            "fallenCause": "ကျည်မှန်"
        },
        {
            "heroName": "ဆလိုင်းနိုင်အောင်",
            "fallenDay": "2021-06-29",
            "heroAge": "22",
            "heroGender": "m",
            "fallenCity": "ဖလမ်း",
            "fallenState": "ချင်း",
            "fallenPlace": "",
            "heroPlace": "",
            "fallenCause": "ကျည်မှန်"
        },
        {
            "heroName": "ဆလိုင်းဗန်ဘွဲ့",
            "fallenDay": "2021-06-29",
            "heroAge": "22",
            "heroGender": "m",
            "fallenCity": "ဖလမ်း",
            "fallenState": "ချင်း",
            "fallenPlace": "",
            "heroPlace": "",
            "fallenCause": "ကျည်မှန်"
        },
        {
            "heroName": "ကိုမင်းသူ",
            "fallenDay": "2021-08-18",
            "heroAge": "22",
            "heroGender": "m",
            "fallenCity": "Unkown",
            "fallenState": "မသိရှိရသေး",
            "fallenPlace": "",
            "heroPlace": "",
            "fallenCause": ""
        },
        {
            "heroName": "ကိုနို့",
            "fallenDay": "2021-09-29",
            "heroAge": "22",
            "heroGender": "m",
            "fallenCity": "လွိုင်ကော်",
            "fallenState": "ကယား",
            "fallenPlace": "လွိုင်ကော်မြို့နယ်၊ ကုန်းသာကျေးရွာ",
            "heroPlace": "ဖယ်ခုံမြို့နယ်၊ လယ်ထွန်ကျေးရွာ",
            "fallenCause": "ကျည်မှန်"
        },
        {
            "heroName": "ကိုမာရ်ကို",
            "fallenDay": "2021-09-29",
            "heroAge": "22",
            "heroGender": "m",
            "fallenCity": "လွိုင်ကော်",
            "fallenState": "ကယား",
            "fallenPlace": "လွိုင်ကော်မြို့နယ်၊ ကုန်းသာကျေးရွာ",
            "heroPlace": "ဖယ်ခုံမြို့နယ်၊ လယ်ထွန်ကျေးရွာ",
            "fallenCause": "ကျည်မှန်"
        },
        {
            "heroName": "ကိုထွန်းထွန်းငြိမ်း",
            "fallenDay": "2021-11-18",
            "heroAge": "22",
            "heroGender": "m",
            "fallenCity": "ဒီးမော့ဆို",
            "fallenState": "ကယား",
            "fallenPlace": "ဒီးမော့ဆိုမြို့နယ် စံပြ ၆ မိုင်ရွာ၊ ခရစ်ယာန်ဘုရားကျောင်းအနီး",
            "heroPlace": "ဒီးမော့ဆိုမြို့နယ် ငွေတောင်ရွာ",
            "fallenCause": "ကျည်မှန်"
        },
        {
            "heroName": "မချစ်စုဝေ",
            "fallenDay": "2021-11-18",
            "heroAge": "22",
            "heroGender": "f",
            "fallenCity": "ဒီးမော့ဆို",
            "fallenState": "ကယား",
            "fallenPlace": "ဒီးမော့ဆိုမြို့နယ် စံပြ ၆ မိုင်ရွာ၊ ခရစ်ယာန်ဘုရားကျောင်းအနီး",
            "heroPlace": "ဒီးမော့ဆိုမြို့နယ် ငွေတောင်ရွာ",
            "fallenCause": "ကျည်မှန်"
        },
        {
            "heroName": "ကိုထက်ကို",
            "fallenDay": "2021-12-07",
            "heroAge": "22",
            "heroGender": "m",
            "fallenCity": "ဆားလင်းကြီး",
            "fallenState": "စစ်ကိုင်း",
            "fallenPlace": "ဆားလင်းကြီးမြို့နယ်၊ ဒုန်းတောကျေးရွာ",
            "heroPlace": "ဆားလင်းကြီးမြို့နယ်၊ ဒုန်းတောကျေးရွာ",
            "fallenCause": "မီးရှို့သတ်ဖြတ်ခံရ"
        },
        {
            "heroName": "ကိုဇင်မင်းထွန်း",
            "fallenDay": "2021-12-07",
            "heroAge": "22",
            "heroGender": "m",
            "fallenCity": "ဆားလင်းကြီး",
            "fallenState": "စစ်ကိုင်း",
            "fallenPlace": "ဆားလင်းကြီးမြို့နယ်၊ ဒုန်းတောကျေးရွာ",
            "heroPlace": "ဆားလင်းကြီးမြို့နယ်၊ ဒုန်းတောကျေးရွာ",
            "fallenCause": "မီးရှို့သတ်ဖြတ်ခံရ"
        },
        {
            "heroName": "ကိုနိုင်သူအောင်",
            "fallenDay": "2021-12-23",
            "heroAge": "22",
            "heroGender": "m",
            "fallenCity": "မင်းကင်း",
            "fallenState": "စစ်ကိုင်း",
            "fallenPlace": "",
            "heroPlace": "",
            "fallenCause": ""
        },
        {
            "heroName": "ဆလိုင်းဖေဟုန်",
            "fallenDay": "2021-12-26",
            "heroAge": "22",
            "heroGender": "m",
            "fallenCity": "မင်းတပ်",
            "fallenState": "ချင်း",
            "fallenPlace": "မင်းတပ်မြို့နယ်၊ ရှစ်မွှေးကျေးရွာ",
            "heroPlace": "",
            "fallenCause": "ဖမ်းဆီးခံရအပြီး ညင်းပန်းနှိပ်စက်ကာ ခန္ဒာကိုယ်အစိတ်အပိုင်းများလှီးဖြတ်ကာ သတ်ဖြတ်ခံရ"
        },
        {
            "heroName": "ကိုမျိုးလွင်ဦး",
            "fallenDay": "2021-12-31",
            "heroAge": "22",
            "heroGender": "m",
            "fallenCity": "ဒီပဲယင်း",
            "fallenState": "စစ်ကိုင်း",
            "fallenPlace": "",
            "heroPlace": "",
            "fallenCause": "မိုင်းမှန်"
        },
        {
            "heroName": "ထန်းအွမ် (Thang Awm)",
            "fallenDay": "2022-01-14",
            "heroAge": "22",
            "heroGender": "m",
            "fallenCity": "မတူပီ",
            "fallenState": "ချင်း",
            "fallenPlace": "",
            "heroPlace": "",
            "fallenCause": "မိုင်းမှန်"
        },
        {
            "heroName": "ကိုရဲရင့်ဇော်",
            "fallenDay": "2022-01-15",
            "heroAge": "22",
            "heroGender": "m",
            "fallenCity": "ကလေး",
            "fallenState": "စစ်ကိုင်း",
            "fallenPlace": "ကလေးမြို့နယ်၊ အောင်မြေမာန်ရပ်",
            "heroPlace": "",
            "fallenCause": "ကျည်မှန်"
        },
        {
            "heroName": "ကိုနိုင်နှောင်းထက်",
            "fallenDay": "2022-01-16",
            "heroAge": "22",
            "heroGender": "m",
            "fallenCity": "ထီးချိုင့်",
            "fallenState": "စစ်ကိုင်း",
            "fallenPlace": "ထီးချိုင့်မြို့နယ်၊ ကျွန်းပင်သာကျေးရွာ အနီး",
            "heroPlace": "",
            "fallenCause": "ဖမ်းဆီးခံရအပြီး သတ်ဖြတ်ခံရ"
        },
        {
            "heroName": "ကိုဇင်မျိုးဦး",
            "fallenDay": "2022-01-24",
            "heroAge": "22",
            "heroGender": "m",
            "fallenCity": "ဒီးမော့ဆို",
            "fallenState": "ကယား",
            "fallenPlace": "ဒီးမော့ဆိုမြို့နယ်၊ စံပြင် (၆)မိုင်ကျေးရွာ၊ ဟိုဖိတ်ရွာအနီး",
            "heroPlace": "",
            "fallenCause": ""
        }
    ]
}