{
    "items": [
        {
            "heroName": "ဦးဝင်းကြိုင်",
            "fallenDay": "2021-07-20",
            "heroAge": "65",
            "heroGender": "m",
            "fallenCity": "အင်းစိန်",
            "fallenState": "ရန်ကုန်",
            "fallenPlace": "အင်းစိန်ထောင်",
            "heroPlace": "လှိုင်သာယာမြို့နယ်၊ ရန်ကုန်မြို့၊",
            "fallenCause": "အင်းစိန်ထောင်တွင် ကွယ်လွန်"
        },
        {
            "heroName": "ဒေါ်ဝင်းရီ (ခ) ဒေါ်ဝင်းကြည်",
            "fallenDay": "2021-12-08",
            "heroAge": "65",
            "heroGender": "f",
            "fallenCity": "ဆားလင်းကြီး",
            "fallenState": "စစ်ကိုင်း",
            "fallenPlace": "ဆားလင်းကြီးမြို့နယ်၊ ဒုန်းတောကျေးရွာ",
            "heroPlace": "ဆားလင်းကြီးမြို့နယ်၊ ဒုန်းတောကျေးရွာ",
            "fallenCause": "ကျည်မှန်"
        },
        {
            "heroName": "ဦးစိန်ဝင်း",
            "fallenDay": "2022-01-20",
            "heroAge": "65",
            "heroGender": "m",
            "fallenCity": "ရေစကြို",
            "fallenState": "မကွေး",
            "fallenPlace": "ရေစကြိုမြို့နယ်၊ နေရင်းရွာ",
            "heroPlace": "ရေစကြိုမြို့နယ်၊ နေရင်းရွာ",
            "fallenCause": "ကျည်မှန်"
        },
        {
            "heroName": "ဦးလှရွှေ",
            "fallenDay": "2022-02-14",
            "heroAge": "65",
            "heroGender": "m",
            "fallenCity": "ပုလဲ",
            "fallenState": "စစ်ကိုင်း",
            "fallenPlace": "ပုလဲမြို့နယ်၊ ဇီးဖြူကုန်းရွာ",
            "heroPlace": "ပုလဲမြို့နယ်၊ ဇီးဖြူကုန်းရွာ",
            "fallenCause": "မီးရှို့သတ်ဖြတ်ခံရ"
        }
    ]
}